fontawesome_converter/__init__.py
fontawesome_converter/__main__.py
fontawesome_converter/cli.py
fontawesome_converter/converter.py
fontawesome_converter-1.1.0.dist-info/licenses/LICENSE
fontawesome_converter-1.1.0.dist-info/METADATA
fontawesome_converter-1.1.0.dist-info/WHEEL
fontawesome_converter-1.1.0.dist-info/entry_points.txt
fontawesome_converter-1.1.0.dist-info/top_level.txt
fontawesome_converter-1.1.0.dist-info/RECORD
