Metadata-Version: 2.4
Name: fontawesome-converter
Version: 1.1.0
Summary: Convert FontAwesome icons to PNG format
Home-page: https://github.com/SakuraPuare/fontawesome-converter
Author: SakuraPuare
Author-email: sakurapuare@sakurapuare.com
Classifier: Programming Language :: Python :: 3
Classifier: License :: OSI Approved :: MIT License
Classifier: Operating System :: OS Independent
Requires-Python: >=3.10
License-File: LICENSE
Requires-Dist: click>=8.0.0
Requires-Dist: loguru>=0.6.0
Requires-Dist: tqdm>=4.60.0
Requires-Dist: cairosvg>=2.5.0
Requires-Dist: Pillow>=9.0.0
Dynamic: author
Dynamic: author-email
Dynamic: classifier
Dynamic: description
Dynamic: description-content-type
Dynamic: home-page
Dynamic: license-file
Dynamic: requires-dist
Dynamic: requires-python
Dynamic: summary
